AUTHORS
LICENSE
MANIFEST.in
README.md
requirements.txt
setup.py
rep/__init__.py
rep/plotting.py
rep/utils.py
rep.egg-info/PKG-INFO
rep.egg-info/SOURCES.txt
rep.egg-info/dependency_links.txt
rep.egg-info/requires.txt
rep.egg-info/top_level.txt
rep/data/__init__.py
rep/data/storage.py
rep/estimators/__init__.py
rep/estimators/_tmvaFactory.py
rep/estimators/_tmvaReader.py
rep/estimators/interface.py
rep/estimators/neurolab.py
rep/estimators/pybrain.py
rep/estimators/sklearn.py
rep/estimators/theanets.py
rep/estimators/tmva.py
rep/estimators/utils.py
rep/estimators/xgboost.py
rep/metaml/__init__.py
rep/metaml/_cache.py
rep/metaml/cache.py
rep/metaml/factory.py
rep/metaml/folding.py
rep/metaml/gridsearch.py
rep/metaml/stacking.py
rep/metaml/utils.py
rep/report/__init__.py
rep/report/_base.py
rep/report/classification.py
rep/report/metrics.py
rep/report/regression.py
rep/test/__init__.py
rep/test/test_estimators.py
rep/test/test_notebooks.py