Metadata-Version: 1.1
Name: rep
Version: 0.6.6
Summary: infrastructure for computational experiments in machine learning
Home-page: https://github.com/yandex/rep
Author: The following authors have created the source code of "Reproducible Experiment Platform"
